MANIFEST.in
PluginCompleteLikeEclipse.py
README.rst
setup.cfg
setup.py
scribes/__init__.py
scribes.edit.complete_like_eclipse.egg-info/PKG-INFO
scribes.edit.complete_like_eclipse.egg-info/SOURCES.txt
scribes.edit.complete_like_eclipse.egg-info/dependency_links.txt
scribes.edit.complete_like_eclipse.egg-info/namespace_packages.txt
scribes.edit.complete_like_eclipse.egg-info/not-zip-safe
scribes.edit.complete_like_eclipse.egg-info/requires.txt
scribes.edit.complete_like_eclipse.egg-info/top_level.txt
scribes/edit/__init__.py
scribes/edit/complete_like_eclipse/BufferMonitor.py
scribes/edit/complete_like_eclipse/DictionaryManager.py
scribes/edit/complete_like_eclipse/IndexerProcessManager.py
scribes/edit/complete_like_eclipse/ProcessCommunicator.py
scribes/edit/complete_like_eclipse/TextExtractor.py
scribes/edit/complete_like_eclipse/__init__.py
scribes/edit/complete_like_eclipse/signals.py
scribes/edit/complete_like_eclipse/IndexerProcess/DBusService.py
scribes/edit/complete_like_eclipse/IndexerProcess/DictionaryGenerator.py
scribes/edit/complete_like_eclipse/IndexerProcess/IndexerManager.py
scribes/edit/complete_like_eclipse/IndexerProcess/IndexerProcessMonitor.py
scribes/edit/complete_like_eclipse/IndexerProcess/JobSpooler.py
scribes/edit/complete_like_eclipse/IndexerProcess/ScribesWordCompletionIndexer.py
scribes/edit/complete_like_eclipse/IndexerProcess/__init__.py