Metadata-Version: 1.0
Name: scribes.edit.complete-like-eclipse
Version: 0.2.4
Summary: Eclipse like word completition
Home-page: http://github.com/baverman/scribes-goodies
Author: Anton Bobrov
Author-email: bobrov@vl.ru
License: UNKNOWN
Platform: UNKNOWN
